xspider/__init__.py
xspider/core/__init__.py
xspider/core/component.py
xspider/core/configer/__init__.py
xspider/core/configer/default_config.py
xspider/core/crawler.py
xspider/core/crawler_process.py
xspider/core/downloader.py
xspider/core/engine.py
xspider/core/processor.py
xspider/core/scheduler.py
xspider/core/tasker.py
xspider/exceptions.py
xspider/http/__init__.py
xspider/http/request/__init__.py
xspider/http/response/__init__.py
xspider/item/__init__.py
xspider/spider/__init__.py
xspider/type/__init__.py
xspider/type/types.py
xspider/type/validators.py
xspider/utils/__init__.py
xspider/utils/cookies.py
xspider/utils/datetime.py
xspider/utils/html.py
xspider/utils/project.py
xspider/utils/spider_priority_queue.py
xspider/utils/sql.py
xspider/utils/string.py
xspider-1.0.0.20250521.dist-info/LICENSE
xspider-1.0.0.20250521.dist-info/METADATA
xspider-1.0.0.20250521.dist-info/WHEEL
xspider-1.0.0.20250521.dist-info/RECORD
