Metadata-Version: 2.3
Name: xspider
Version: 1.0.0.20250521
Summary: 
Author: mathewgeola
Author-email: mathewgeola@gmail.com
Requires-Python: >=3.12
Classifier: Programming Language :: Python :: 3
Classifier: Programming Language :: Python :: 3.12
Classifier: Programming Language :: Python :: 3.13
Requires-Dist: aiohttp (>=3.11.18,<4.0.0)
Requires-Dist: arrow (>=1.3.0,<2.0.0)
Requires-Dist: htmlmin (>=0.1.12,<0.2.0)
Requires-Dist: httpx (>=0.28.1,<0.29.0)
Requires-Dist: parsel (>=1.10.0,<2.0.0)
Requires-Dist: requests (>=2.32.3,<3.0.0)
Requires-Dist: sqlparse (>=0.5.3,<0.6.0)
Requires-Dist: ujson (>=5.10.0,<6.0.0)
